smartobjects/__init__.py
smartobjects/__version__.py
smartobjects/api_manager.py
smartobjects/smartobjects_client.py
smartobjects/helpers/__init__.py
smartobjects/ingestion/__init__.py
smartobjects/ingestion/events.py
smartobjects/ingestion/objects.py
smartobjects/ingestion/owners.py
smartobjects/model/__init__.py
smartobjects/model/model.py
smartobjects/restitution/__init__.py
smartobjects/restitution/search.py
smartobjects-1.4.0.dist-info/LICENSE
smartobjects-1.4.0.dist-info/METADATA
smartobjects-1.4.0.dist-info/WHEEL
smartobjects-1.4.0.dist-info/top_level.txt
smartobjects-1.4.0.dist-info/RECORD
