Metadata-Version: 2.1
Name: smartobjects
Version: 1.4.0
Summary: Python client to access mnubo's SmartObjects ingestion and restitution APIs
Home-page: https://github.com/mnubo/smartobjects-python-client
Author: mnubo, inc.
Author-email: support@mnubo.com
License: UNKNOWN
Keywords: mnubo,api,sdk,iot,smartobjects
Platform: UNKNOWN
Classifier: Operating System :: OS Independent
Classifier: Programming Language :: Python
Provides-Extra: pandas
